byubit/__init__.py
byubit/bit.py
byubit/renderers/__init__.py
byubit/renderers/html/render_bit.html
byubit/renderers/html/render_bit.js
byubit/renderers/html_renderer.py
byubit/rendering.py
byubit-0.9.3.dist-info/LICENSE
byubit-0.9.3.dist-info/METADATA
byubit-0.9.3.dist-info/WHEEL
byubit-0.9.3.dist-info/RECORD
