Metadata-Version: 2.1
Name: byubit
Version: 0.9.3
Summary: A library for teaching beginners how to program
License: MIT
Author: Gordon Bean
Author-email: gbean@cs.byu.edu
Requires-Python: >=3.8,<4.0
Classifier: License :: OSI Approved :: MIT License
Classifier: Programming Language :: Python :: 3
Classifier: Programming Language :: Python :: 3.8
Classifier: Programming Language :: Python :: 3.9
Classifier: Programming Language :: Python :: 3.10
Classifier: Programming Language :: Python :: 3.11
Classifier: Programming Language :: Python :: 3.12
Classifier: Programming Language :: Python :: 3.13
Requires-Dist: webcolors (>=24.8.0)
